LICENSE
MANIFEST.in
README.md
setup.cfg
setup.py
fwadmin/__init__.py
fwadmin/filtersets.py
fwadmin/forms.py
fwadmin/models.py
fwadmin/navigation.py
fwadmin/tables.py
fwadmin/tasks.py
fwadmin/urls.py
fwadmin/views.py
fwadmin/workflows.py
fwadmin.egg-info/PKG-INFO
fwadmin.egg-info/SOURCES.txt
fwadmin.egg-info/dependency_links.txt
fwadmin.egg-info/not-zip-safe
fwadmin.egg-info/requires.txt
fwadmin.egg-info/top_level.txt
fwadmin/api/__init__.py
fwadmin/api/serializers.py
fwadmin/api/urls.py
fwadmin/api/views.py
fwadmin/migrations/0001_initial.py
fwadmin/migrations/__init__.py
fwadmin/scripts/FWAdmin.py
fwadmin/templates/fwadmin/devicegroup.html
fwadmin/templates/fwadmin/dynamiclist.html
fwadmin/templates/fwadmin/firewall.html
fwadmin/templates/fwadmin/sessionrequest.html
fwadmin/templates/fwadmin/sessionrequest_bulk_manage.html
fwadmin/templates/fwadmin/sessionrequest_list.html
fwadmin/templates/fwadmin/sessionrequest_manage.html
fwadmin/templates/fwadmin/buttons/approve.html
fwadmin/templates/fwadmin/buttons/reject.html
fwadmin/templates/fwadmin/buttons/self_approve.html
fwadmin/templates/fwadmin/htmx/manage_form.html
fwadmin/templatetags/__init__.py
fwadmin/templatetags/fwadmin_buttons.py
fwadmin/tests/__init__.py
fwadmin/tests/test.py