Metadata-Version: 2.1
Name: fwadmin
Version: 0.8.0
Summary: Firewall manager and viewer plugin for Netbox
Home-page: https://github.com/dainok/fwadmin
Author: Andrea Dainese
Author-email: andrea@adainese.it
License: GNU v3.0
Project-URL: Source, https://github.com/dainok/fwadmin
Platform: UNKNOWN
Classifier: Programming Language :: Python
Classifier: Programming Language :: Python :: 3
Classifier: Programming Language :: Python :: 3 :: Only
License-File: LICENSE
